{
  "identifier": "windsquid.catpuccin.sn",
  "name": "Catpuccin",
  "content_type": "SN|Theme",
  "area": "themes",
  "version": "1.0.1",
  "description": "Catpuccin theme for Standard Notes",
  "url": "https://cdn.jsdelivr.net/gh/windsquid/catppuccin.sn@v1.0.1/dist/dist.css",
  "download_url": "https://github.com/windsquid/catppuccin.sn/archive/refs/tags/v1.0.1.zip",
  "latest_url": "https://cdn.jsdelivr.net/gh/windsquid/catppuccin.sn@main/ext.json",
  "marketing_url": "https://github.com/windsquid/catppuccin.sn",
  "thumbnail_url": "https://github.com/windsquid/catppuccin.sn/preview.png"
}
